setup.cfg
setup.py
AudioBible.egg-info/PKG-INFO
AudioBible.egg-info/SOURCES.txt
AudioBible.egg-info/dependency_links.txt
AudioBible.egg-info/entry_points.txt
AudioBible.egg-info/requires.txt
AudioBible.egg-info/top_level.txt
audiobible/__init__.py
audiobible/book.py
audiobible/download.py
audiobible/kjv/__init__.py
audiobible/kjv/items.py
audiobible/kjv/middlewares.py
audiobible/kjv/pipelines.py
audiobible/kjv/settings.py
audiobible/kjv/bible/__init__.py
audiobible/kjv/bible/bible.py
audiobible/kjv/dictionary/__init__.py
audiobible/kjv/dictionary/dictionary.py
audiobible/kjv/speakers/__init__.py
audiobible/kjv/speakers/speakers.py
audiobible/kjv/topics/__init__.py
audiobible/kjv/topics/topics.py
tests/__init__.py