Metadata-Version: 1.1
Name: AudioBible
Version: 0.7.9
Summary: KJV Audio Bible
Home-page: https://github.com/gxela/AudioBible
Author: Alex Goretoy
Author-email: alex@goretoy.com
License: MIT
Platform: UNKNOWN
Classifier: Development Status :: 4 - Beta
Classifier: Environment :: Console
Classifier: Framework :: Scrapy
Classifier: Intended Audience :: Religion
Classifier: License :: Public Domain
Classifier: Natural Language :: English
Classifier: Operating System :: OS Independent
Classifier: Programming Language :: Python
Classifier: Topic :: Religion
